{
  "classes": [
    {
      "class_name": "eTMF",
      "reasoning": "Document explicitly self-identifies as 'eTMF-001 — TRIAL MASTER FILE INDEX' in the title and provides a structured index of Trial Master File artifacts organized by DIA TMF Reference Model zones and sections, tracking document status, versions, and filing dates.",
      "confidence": 1.0
    }
  ],
  "nct_id": "",
  "eudract_id": "",
  "eu_ct_id": "",
  "isrctn_id": "",
  "utn_id": "",
  "ind_number": "",
  "cta_number": "",
  "sponsor_protocol_id": "BIORCE-ONC-2023-001",
  "sponsor_name": "Biorce Therapeutics S.L.",
  "trial_title": "",
  "trial_acronym": "",
  "intervention": "",
  "indication": "",
  "therapeutic_area": "Oncology",
  "phase": "",
  "version": "1.3",
  "version_ordinal": 1,
  "country": "",
  "site_id": "",
  "summary": "This is a Trial Master File index document (eTMF-001) for study BIORCE-ONC-2023-001, maintained in Veeva Vault. It provides a comprehensive index of all TMF artifacts organized according to the DIA TMF Reference Model v3.0, tracking document filing status, versions, ownership, and overall TMF health metrics. The index shows 61% of artifacts are complete with ongoing site-level documentation in progress.",
  "references_to": [
    "Protocol and Amendments v2.1",
    "Protocol Signature Page v2.1",
    "Protocol Deviation Log",
    "Investigator Brochure Ed. 2",
    "IB Acknowledgement",
    "Sample CRF / eCRF Guidelines v2.1",
    "eCRF User Manual v1.4",
    "Statistical Analysis Plan v1.1",
    "Data Management Plan v1.0",
    "Edit Check Specifications",
    "Regulatory Authority Approval (EudraCT)",
    "EudraCT Registration",
    "Central Ethics Committee Approval",
    "Site EC Approvals",
    "Informed Consent Forms — Approved v2.1",
    "Re-Consent Forms v3.0",
    "Insurance/Indemnity Certificate",
    "Financial Disclosure Forms",
    "Site Initiation Visit Reports",
    "Investigator CVs",
    "Lab Accreditation Certificates",
    "Normal Ranges (per site)",
    "Drug Accountability Logs",
    "Monitor Visit Reports",
    "Screening and Enrolment Logs",
    "Amendment 1",
    "Amendment 2",
    "DIA TMF Reference Model v3.0"
  ],
  "filename": "File_016.md",
  "raw_sha256": "0290c1ca04ba1364f34d2b1c8c6c887c7063ad139c34d18d012c3762873bd163"
}